permify_async/__init__.py
permify_async/api_client.py
permify_async/api_response.py
permify_async/configuration.py
permify_async/exceptions.py
permify_async/py.typed
permify_async/rest.py
permify_async/api/__init__.py
permify_async/api/bundle_api.py
permify_async/api/data_api.py
permify_async/api/permission_api.py
permify_async/api/schema_api.py
permify_async/api/tenancy_api.py
permify_async/api/watch_api.py
permify_async/models/__init__.py
permify_async/models/abstract_type.py
permify_async/models/any.py
permify_async/models/argument.py
permify_async/models/attribute.py
permify_async/models/attribute_definition.py
permify_async/models/attribute_filter.py
permify_async/models/attribute_read_request_metadata.py
permify_async/models/attribute_read_response.py
permify_async/models/attribute_type.py
permify_async/models/bundle_delete_body.py
permify_async/models/bundle_delete_request.py
permify_async/models/bundle_delete_response.py
permify_async/models/bundle_read_body.py
permify_async/models/bundle_read_request.py
permify_async/models/bundle_read_response.py
permify_async/models/bundle_run_request.py
permify_async/models/bundle_run_response.py
permify_async/models/bundle_write_body.py
permify_async/models/bundle_write_request.py
permify_async/models/bundle_write_response.py
permify_async/models/check_body.py
permify_async/models/check_result.py
permify_async/models/checked_expr.py
permify_async/models/child.py
permify_async/models/comprehension.py
permify_async/models/computed_attribute.py
permify_async/models/computed_user_set.py
permify_async/models/constant.py
permify_async/models/context.py
permify_async/models/context_attribute.py
permify_async/models/create_list.py
permify_async/models/create_struct.py
permify_async/models/data_attributes_read_request.py
permify_async/models/data_bundle.py
permify_async/models/data_change.py
permify_async/models/data_change_operation.py
permify_async/models/data_changes.py
permify_async/models/data_delete_body.py
permify_async-1.0.51.dist-info/METADATA
permify_async-1.0.51.dist-info/WHEEL
permify_async-1.0.51.dist-info/top_level.txt
permify_async-1.0.51.dist-info/RECORD
